dep_checker/__init__.py
dep_checker/__main__.py
dep_checker/_stdlib_list.py
dep_checker/config.py
dep_checker/py.typed
dep_checker/utils.py
dep_checker-0.9.0.dist-info/LICENSE
dep_checker-0.9.0.dist-info/METADATA
dep_checker-0.9.0.dist-info/WHEEL
dep_checker-0.9.0.dist-info/entry_points.txt
dep_checker-0.9.0.dist-info/RECORD
