Metadata-Version: 2.2
Name: dep-checker
Version: 0.9.0
Summary: Tool to check all requirements are actually required.
Author-email: Dominic Davis-Foster <dominic@davis-foster.co.uk>
License: MIT
Keywords: dependencies,linter,pre-commit
Home-page: https://github.com/python-coincidence/dep_checker
Project-URL: Issue Tracker, https://github.com/python-coincidence/dep_checker/issues
Project-URL: Source Code, https://github.com/python-coincidence/dep_checker
Project-URL: Documentation, https://dep-checker.readthedocs.io/en/latest
Platform: Windows
Platform: macOS
Platform: Linux
Classifier: Development Status :: 4 - Beta
Classifier: Environment :: Console
Classifier: Intended Audience :: Developers
Classifier: License :: OSI Approved :: MIT License
Classifier: Operating System :: OS Independent
Classifier: Programming Language :: Python
Classifier: Programming Language :: Python :: 3 :: Only
Classifier: Programming Language :: Python :: 3.7
Classifier: Programming Language :: Python :: 3.8
Classifier: Programming Language :: Python :: 3.9
Classifier: Programming Language :: Python :: 3.10
Classifier: Programming Language :: Python :: 3.11
Classifier: Programming Language :: Python :: 3.12
Classifier: Programming Language :: Python :: 3.13
Classifier: Programming Language :: Python :: Implementation :: CPython
Classifier: Programming Language :: Python :: Implementation :: PyPy
Classifier: Typing :: Typed
Requires-Python: >=3.7
Requires-Dist: astatine>=0.3.0
Requires-Dist: click>=7.1.2
Requires-Dist: configconfig>=0.4.0
Requires-Dist: consolekit>=0.4.0
Requires-Dist: dom-toml>=0.2.0
Requires-Dist: domdf-python-tools>=3.2.0
Requires-Dist: shippinglabel>=0.1.0
